{
  "key": null,
  "keyPath": "fetch.headers.X-Riot-Token",
  "origin": "https://{region}.api.riotgames.com",
  "regionPath": "originParams.region",
  "retries": 3,
  "maxConcurrent": 2000,
  "distFactor": 1,
  "defaultBuckets": [
    {
      "timespan": 1000,
      "limit": 1,
      "bins": 1,
      "binFactor": 1,
      "overhead": 0
    }
  ],
  "bucketsConfig": {},
  "rateLimitTypeApplication": {
    "name": "application",
    "headerLimit": "x-app-rate-limit",
    "headerCount": "x-app-rate-limit-count"
  },
  "rateLimitTypeMethod": {
    "name": "method",
    "headerLimit": "x-method-rate-limit",
    "headerCount": "x-method-rate-limit-count"
  },
  "defaultRetryAfter": null,
  "headerRetryAfter": "retry-after",
  "headerLimitType": "x-rate-limit-type",
  "defaultLimitType": null,
  "collapseQueryArrays": false,
  "endpoints": {
    "lol": {
      "championMasteryV4": {
        "getAllChampionMasteries": {
          "path": "/lol/champion-mastery/v4/champion-masteries/by-summoner/{summonerId}"
        },
        "getChampionMastery": {
          "path": "/lol/champion-mastery/v4/champion-masteries/by-summoner/{summonerId}/by-champion/{championId}"
        },
        "getChampionMasteryScore": {
          "path": "/lol/champion-mastery/v4/scores/by-summoner/{summonerId}"
        }
      },
      "championV3": {
        "getChampionInfo": {
          "path": "/lol/platform/v3/champion-rotations"
        }
      },
      "clashV1": {
        "getPlayersBySummoner": {
          "path": "/lol/clash/v1/players/by-summoner/{summonerId}"
        },
        "getTeamById": {
          "path": "/lol/clash/v1/teams/{teamId}"
        },
        "getTournaments": {
          "path": "/lol/clash/v1/tournaments"
        },
        "getTournamentByTeam": {
          "path": "/lol/clash/v1/tournaments/by-team/{teamId}"
        },
        "getTournamentById": {
          "path": "/lol/clash/v1/tournaments/{tournamentId}"
        }
      },
      "leagueExpV4": {
        "getLeagueEntries": {
          "path": "/lol/league-exp/v4/entries/{queue}/{tier}/{division}"
        }
      },
      "leagueV4": {
        "getChallengerLeague": {
          "path": "/lol/league/v4/challengerleagues/by-queue/{queue}"
        },
        "getLeagueEntriesForSummoner": {
          "path": "/lol/league/v4/entries/by-summoner/{summonerId}"
        },
        "getLeagueEntries": {
          "path": "/lol/league/v4/entries/{queue}/{tier}/{division}"
        },
        "getGrandmasterLeague": {
          "path": "/lol/league/v4/grandmasterleagues/by-queue/{queue}"
        },
        "getLeagueById": {
          "path": "/lol/league/v4/leagues/{leagueId}"
        },
        "getMasterLeague": {
          "path": "/lol/league/v4/masterleagues/by-queue/{queue}"
        }
      },
      "statusV3": {
        "getShardData": {
          "path": "/lol/status/v3/shard-data"
        }
      },
      "lorRankedV1": {
        "getLeaderboards": {
          "path": "/lor/ranked/v1/leaderboards"
        }
      },
      "matchV4": {
        "getMatchIdsByTournamentCode": {
          "path": "/lol/match/v4/matches/by-tournament-code/{tournamentCode}/ids"
        },
        "getMatch": {
          "path": "/lol/match/v4/matches/{matchId}"
        },
        "getMatchByTournamentCode": {
          "path": "/lol/match/v4/matches/{matchId}/by-tournament-code/{tournamentCode}"
        },
        "getMatchlist": {
          "path": "/lol/match/v4/matchlists/by-account/{accountId}"
        },
        "getMatchTimeline": {
          "path": "/lol/match/v4/timelines/by-match/{matchId}"
        }
      },
      "spectatorV4": {
        "getCurrentGameInfoBySummoner": {
          "path": "/lol/spectator/v4/active-games/by-summoner/{summonerId}"
        },
        "getFeaturedGames": {
          "path": "/lol/spectator/v4/featured-games"
        }
      },
      "summonerV4": {
        "getByAccountId": {
          "path": "/lol/summoner/v4/summoners/by-account/{accountId}"
        },
        "getBySummonerName": {
          "path": "/lol/summoner/v4/summoners/by-name/{summonerName}"
        },
        "getByPUUID": {
          "path": "/lol/summoner/v4/summoners/by-puuid/{puuid}"
        },
        "getBySummonerId": {
          "path": "/lol/summoner/v4/summoners/{summonerId}"
        }
      },
      "thirdPartyCodeV4": {
        "getThirdPartyCodeBySummonerId": {
          "path": "/lol/platform/v4/third-party-code/by-summoner/{summonerId}"
        }
      }
    },
    "tft": {
      "leagueV1": {
        "getChallengerLeague": {
          "path": "/tft/league/v1/challenger"
        },
        "getLeagueEntriesForSummoner": {
          "path": "/tft/league/v1/entries/by-summoner/{summonerId}"
        },
        "getLeagueEntries": {
          "path": "/tft/league/v1/entries/{tier}/{division}"
        },
        "getGrandmasterLeague": {
          "path": "/tft/league/v1/grandmaster"
        },
        "getLeagueById": {
          "path": "/tft/league/v1/leagues/{leagueId}"
        },
        "getMasterLeague": {
          "path": "/tft/league/v1/master"
        }
      },
      "matchV1": {
        "getMatchIdsByPUUID": {
          "path": "/tft/match/v1/matches/by-puuid/{puuid}/ids"
        },
        "getMatch": {
          "path": "/tft/match/v1/matches/{matchId}"
        },
        "*": {
          "regionTable": {
            "br": "americas",
            "eune": "europe",
            "euw": "europe",
            "jp": "asia",
            "kr": "asia",
            "lan": "americas",
            "las": "americas",
            "na": "americas",
            "oce": "americas",
            "tr": "europe",
            "ru": "europe",
            "pbe": "americas",
            "americas": "americas",
            "europe": "europe",
            "asia": "asia"
          }
        }
      },
      "summonerV1": {
        "getByAccountId": {
          "path": "/tft/summoner/v1/summoners/by-account/{accountId}"
        },
        "getBySummonerName": {
          "path": "/tft/summoner/v1/summoners/by-name/{summonerName}"
        },
        "getByPUUID": {
          "path": "/tft/summoner/v1/summoners/by-puuid/{puuid}"
        },
        "getBySummonerId": {
          "path": "/tft/summoner/v1/summoners/{summonerId}"
        }
      }
    },
    "tournament": {
      "stubV4": {
        "createTournamentCode": {
          "path": "/lol/tournament-stub/v4/codes",
          "fetch": {
            "method": "post"
          }
        },
        "getLobbyEventsByCode": {
          "path": "/lol/tournament-stub/v4/lobby-events/by-code/{tournamentCode}"
        },
        "registerProviderData": {
          "path": "/lol/tournament-stub/v4/providers",
          "fetch": {
            "method": "post"
          }
        },
        "registerTournament": {
          "path": "/lol/tournament-stub/v4/tournaments",
          "fetch": {
            "method": "post"
          }
        }
      },
      "v4": {
        "createTournamentCode": {
          "path": "/lol/tournament/v4/codes",
          "fetch": {
            "method": "post"
          }
        },
        "getTournamentCode": {
          "path": "/lol/tournament/v4/codes/{tournamentCode}"
        },
        "updateCode": {
          "path": "/lol/tournament/v4/codes/{tournamentCode}",
          "fetch": {
            "method": "put"
          }
        },
        "getLobbyEventsByCode": {
          "path": "/lol/tournament/v4/lobby-events/by-code/{tournamentCode}"
        },
        "registerProviderData": {
          "path": "/lol/tournament/v4/providers",
          "fetch": {
            "method": "post"
          }
        },
        "registerTournament": {
          "path": "/lol/tournament/v4/tournaments",
          "fetch": {
            "method": "post"
          }
        }
      },
      "*": {
        "regionTable": {
          "br": "americas",
          "eune": "americas",
          "euw": "americas",
          "jp": "americas",
          "kr": "americas",
          "lan": "americas",
          "las": "americas",
          "na": "americas",
          "oce": "americas",
          "tr": "americas",
          "ru": "americas",
          "pbe": "americas",
          "americas": "americas"
        }
      }
    },
    "*": {
      "regionTable": {
        "br": "br1",
        "eune": "eun1",
        "euw": "euw1",
        "jp": "jp1",
        "kr": "kr",
        "lan": "la1",
        "las": "la2",
        "na": "na1",
        "oce": "oc1",
        "tr": "tr1",
        "ru": "ru",
        "pbe": "pbe1"
      }
    }
  }
}